LICENSE.txt
README.md
setup.cfg
setup.py
django_uml.egg-info/PKG-INFO
django_uml.egg-info/SOURCES.txt
django_uml.egg-info/dependency_links.txt
django_uml.egg-info/requires.txt
django_uml.egg-info/top_level.txt
uml_django/__init__.py
uml_django/inspect.py