Metadata-Version: 2.1
Name: django-uml
Version: 1.0.1
Summary: A UML Generator for Django and Django Rest Framework projects
Home-page: https://github.com/Pedro-V8/uml-django
Author: Pedro Vieira
Author-email: pedrophdv@outlook.com
License: MIT
Keywords: generator UML Django
Platform: UNKNOWN
Classifier: Development Status :: 5 - Production/Stable
Classifier: Intended Audience :: Developers
Classifier: License :: OSI Approved :: MIT License
Classifier: Natural Language :: Portuguese (Brazilian)
Classifier: Operating System :: OS Independent
Classifier: Topic :: Software Development :: Internationalization
Classifier: Topic :: Scientific/Engineering :: Physics
License-File: LICENSE.txt
